gcal_sync/__init__.py
gcal_sync/api.py
gcal_sync/auth.py
gcal_sync/const.py
gcal_sync/exceptions.py
gcal_sync/model.py
gcal_sync/py.typed
gcal_sync/store.py
gcal_sync/sync.py
gcal_sync/timeline.py
gcal_sync-9.0.0.dist-info/licenses/LICENSE
gcal_sync-9.0.0.dist-info/METADATA
gcal_sync-9.0.0.dist-info/WHEEL
gcal_sync-9.0.0.dist-info/top_level.txt
gcal_sync-9.0.0.dist-info/RECORD
