Metadata-Version: 2.4
Name: gcal_sync
Version: 9.0.0
Summary: A python library for syncing Google Calendar to local storage
Author-email: Allen Porter <allen.porter@gmail.com>
License-Expression: Apache-2.0
Project-URL: Source, https://github.com/allenporter/gcal_sync
Requires-Python: >=3.13
License-File: LICENSE
Requires-Dist: aiohttp>=3.8.1
Requires-Dist: ical>=11.0.0
Requires-Dist: pydantic>=2.10.4
Dynamic: license-file
